django_basic_app/__init__.py
django_basic_app/admin.py
django_basic_app/apps.py
django_basic_app/asgi.py
django_basic_app/models.py
django_basic_app/settings.py
django_basic_app/tests.py
django_basic_app/urls.py
django_basic_app/views.py
django_basic_app/wsgi.py
django_basic_app/__pycache__/__init__.cpython-310.pyc
django_basic_app/__pycache__/admin.cpython-310.pyc
django_basic_app/__pycache__/apps.cpython-310.pyc
django_basic_app/__pycache__/models.cpython-310.pyc
django_basic_app/__pycache__/settings.cpython-310.pyc
django_basic_app/__pycache__/urls.cpython-310.pyc
django_basic_app/__pycache__/views.cpython-310.pyc
django_basic_app/__pycache__/wsgi.cpython-310.pyc
melodie_django_basic_app-0.2.0.dist-info/licenses/LICENSE
melodie_django_basic_app-0.2.0.dist-info/METADATA
melodie_django_basic_app-0.2.0.dist-info/WHEEL
melodie_django_basic_app-0.2.0.dist-info/top_level.txt
melodie_django_basic_app-0.2.0.dist-info/RECORD
